LinghunQiyue/Dockerfile
LinghunQiyue/README.md
LinghunQiyue/__init__.py
LinghunQiyue/__main__.py
LinghunQiyue/file.epub
LinghunQiyue/index.html
LinghunQiyue/css/__init__.py
LinghunQiyue/css/annotations.css
LinghunQiyue/css/main.css
LinghunQiyue/css/normalize.css
LinghunQiyue/css/popup.css
LinghunQiyue/font/__init__.py
LinghunQiyue/font/fontello.eot
LinghunQiyue/font/fontello.svg
LinghunQiyue/font/fontello.ttf
LinghunQiyue/font/fontello.woff
LinghunQiyue/img/__init__.py
LinghunQiyue/img/annotator-glyph-sprite.png
LinghunQiyue/img/annotator-icon-sprite.png
LinghunQiyue/img/apple-touch-icon.png
LinghunQiyue/img/cancelfullscreen.png
LinghunQiyue/img/close.png
LinghunQiyue/img/fullscreen.png
LinghunQiyue/img/loader.gif
LinghunQiyue/img/menu-icon.png
LinghunQiyue/img/save.png
LinghunQiyue/img/saved.png
LinghunQiyue/img/settings-s.png
LinghunQiyue/img/settings.png
LinghunQiyue/img/star.png
LinghunQiyue/js/__init__.py
LinghunQiyue/js/epub.js
LinghunQiyue/js/epub.min.js
LinghunQiyue/js/epub.min.map
LinghunQiyue/js/hooks.min.js
LinghunQiyue/js/hooks.min.map
LinghunQiyue/js/reader.js
LinghunQiyue/js/reader.js.map
LinghunQiyue/js/reader.min.js
LinghunQiyue/js/reader.min.map
LinghunQiyue/js/hooks/__init__.py
LinghunQiyue/js/hooks/extensions/__init__.py
LinghunQiyue/js/hooks/extensions/highlight.js
LinghunQiyue/js/libs/__init__.py
LinghunQiyue/js/libs/jquery.min.js
LinghunQiyue/js/libs/localforage.min.js
LinghunQiyue/js/libs/screenfull.js
LinghunQiyue/js/libs/screenfull.min.js
LinghunQiyue/js/libs/zip.min.js
LinghunQiyue/js/plugins/__init__.py
LinghunQiyue/js/plugins/hypothesis.js
LinghunQiyue/js/plugins/search.js
linghun_qiyue-2022.10.3.0.dist-info/METADATA
linghun_qiyue-2022.10.3.0.dist-info/WHEEL
linghun_qiyue-2022.10.3.0.dist-info/entry_points.txt
linghun_qiyue-2022.10.3.0.dist-info/top_level.txt
linghun_qiyue-2022.10.3.0.dist-info/RECORD
